langchain_mistralai/__init__.py
langchain_mistralai/chat_models.py
langchain_mistralai/embeddings.py
langchain_mistralai/py.typed
gigachain_mistralai-0.1.12.dist-info/LICENSE
gigachain_mistralai-0.1.12.dist-info/METADATA
gigachain_mistralai-0.1.12.dist-info/WHEEL
gigachain_mistralai-0.1.12.dist-info/RECORD
