Metadata-Version: 2.1
Name: gigachain-mistralai
Version: 0.1.12
Summary: An integration package connecting Mistral and GigaChain
Home-page: https://github.com/ai-forever/gigachain
License: MIT
Requires-Python: >=3.8.1,<4.0
Classifier: License :: OSI Approved :: MIT License
Classifier: Programming Language :: Python :: 3
Classifier: Programming Language :: Python :: 3.9
Classifier: Programming Language :: Python :: 3.10
Classifier: Programming Language :: Python :: 3.11
Classifier: Programming Language :: Python :: 3.12
Requires-Dist: gigachain-core (>=0.2.26,<0.3.0)
Requires-Dist: httpx (>=0.25.2,<1)
Requires-Dist: httpx-sse (>=0.3.1,<1)
Requires-Dist: tokenizers (>=0.15.1,<1)
Project-URL: Repository, https://github.com/ai-forever/gigachain
Project-URL: Release Notes, https://github.com/ai-forever/gigachain/releases?q=tag%3A%22gigachain-mistralai%3D%3D0%22&expanded=true
Project-URL: Source Code, https://github.com/ai-forever/gigachain/tree/master/libs/partners/mistralai
